mylib039/__init__.py
mylib1039-0.1.dist-info/LICENSE.txt
mylib1039-0.1.dist-info/METADATA
mylib1039-0.1.dist-info/WHEEL
mylib1039-0.1.dist-info/top_level.txt
mylib1039-0.1.dist-info/RECORD
