Metadata-Version: 2.1
Name: mylib1039
Version: 0.1
Summary: for welcoming to package creation
Author: Shraddha
Author-email: shraddha4320@gmail.com
Classifier: Programming Language :: Python :: 3
Classifier: License :: OSI Approved :: MIT License
Classifier: Operating System :: OS Independent
License-File: LICENSE.txt
